<record>
	<id>432</id>
	<language>Kankanay, Northern</language>
	<author>D. Hettick in Reid (1971)</author>
	<silcode>xnn</silcode>
	<glottocode>nort2877</glottocode>
	<notes>Reid, L.A. (1971). Philippine Minor Languages: Word Lists and Phonologies. Oceanic Linguistics Special Publication no. 8. University of Hawaii Press.</notes>
	<problems></problems>
	<classification>Austronesian, Malayo-Polynesian, Philippine, Northern Luzon, Meso-Cordilleran, South-Central Cordilleran, Central Cordilleran, North Central Cordilleran, Nuclear Cordilleran, Bontok-Kankanay, Kankanay</classification>
	<typedby>Janet Moody</typedby>
	<checkedby></checkedby>
	<source>@book{136553,
  address               = {[Honolulu]},
  note                  = {Bibliography: p. [241]},
  pages                 = {xii+239},
  publisher             = {Univ. of Hawaii Press},
  series                = {Oceanic linguistics special publication},
  title                 = {Philippine minor languages: word lists and phonologies},
  volume                = {8},
  year                  = {1971},
  bibtexkey             = {reid_minor-phonologies1971},
  class_loc             = {PL5525},
  document_type         = {B},
  fn                    = {papua\reid_philippine-minor1971.pdf},
  hhtype                = {overview;comparative;wordlist},
  inlg                  = {English [eng]},
  inlg_code             = {eng},
  internetarchive_id    = {rosettaproject_syb_phon-1},
  isbn                  = {9780870226915},
  macro_area            = {Papua},
  mpi_eva_library_shelf = {PL 5525 PHI 1971},
  src                   = {hh, mpieva, wals},
  srctrickle            = {hh#hvw:Reid:Philippine-Minor, mpieva#1971Philippi, wals#4987},
  subject_headings      = {Philippine languages–Glossaries, vocabularies, etc., Philippine languages–Phonology, Philippine languages–Glossaries, vocabularies, etc. – Philippine languages–Phonology},
  author                = {Reid, Lawrence Andrew},
  editor                = {Reid, Lawrence Andrew}
}</source>
</record>

<record>
	<latitude>16.89816268966783852079</latitude>
	<longitude>120.95961821795660284806</longitude>
</record>

<record>
	<id>114189</id>
	<word_id>1</word_id>
	<word>hand</word>
	<item>lɨ'dɨng</item>
	<annotation>&quot;finger&quot;</annotation>
	<loan></loan>
	<cognacy></cognacy>
	<pmpcognacy></pmpcognacy>
</record>

<record>
	<id>114190</id>
	<word_id>2</word_id>
	<word>left</word>
	<item>kani'gid</item>
	<annotation></annotation>
	<loan></loan>
	<cognacy>36</cognacy>
	<pmpcognacy></pmpcognacy>
</record>

<record>
	<id>114191</id>
	<word_id>3</word_id>
	<word>right</word>
	<item>kana'wan</item>
	<annotation></annotation>
	<loan></loan>
	<cognacy>1,67</cognacy>
	<pmpcognacy></pmpcognacy>
</record>

<record>
	<id>114192</id>
	<word_id>4</word_id>
	<word>leg/foot</word>
	<item>'siki</item>
	<annotation></annotation>
	<loan></loan>
	<cognacy>24</cognacy>
	<pmpcognacy></pmpcognacy>
</record>

<record>
	<id>114193</id>
	<word_id>5</word_id>
	<word>to walk</word>
	<item>mɨn'daʔan</item>
	<annotation></annotation>
	<loan></loan>
	<cognacy>21</cognacy>
	<pmpcognacy></pmpcognacy>
</record>

<record>
	<id>114194</id>
	<word_id>8</word_id>
	<word>to turn</word>
	<item>liw'liwɨs</item>
	<annotation></annotation>
	<loan></loan>
	<cognacy>76</cognacy>
	<pmpcognacy></pmpcognacy>
</record>

<record>
	<id>114195</id>
	<word_id>9</word_id>
	<word>to swim</word>
	<item>mɨn'saʔay</item>
	<annotation></annotation>
	<loan></loan>
	<cognacy></cognacy>
	<pmpcognacy></pmpcognacy>
</record>

<record>
	<id>114196</id>
	<word_id>10</word_id>
	<word>dirty</word>
	<item>na'kilot</item>
	<annotation></annotation>
	<loan></loan>
	<cognacy>57</cognacy>
	<pmpcognacy></pmpcognacy>
</record>

<record>
	<id>114197</id>
	<word_id>11</word_id>
	<word>dust</word>
	<item>'tapok</item>
	<annotation></annotation>
	<loan></loan>
	<cognacy>47</cognacy>
	<pmpcognacy></pmpcognacy>
</record>

<record>
	<id>114198</id>
	<word_id>12</word_id>
	<word>skin</word>
	<item>kol'lop</item>
	<annotation></annotation>
	<loan></loan>
	<cognacy></cognacy>
	<pmpcognacy></pmpcognacy>
</record>

<record>
	<id>114199</id>
	<word_id>13</word_id>
	<word>back</word>
	<item>'ʔɨdɨg</item>
	<annotation></annotation>
	<loan></loan>
	<cognacy>21</cognacy>
	<pmpcognacy></pmpcognacy>
</record>

<record>
	<id>114200</id>
	<word_id>14</word_id>
	<word>belly</word>
	<item>ʔɨ'gɨs</item>
	<annotation></annotation>
	<loan></loan>
	<cognacy>53</cognacy>
	<pmpcognacy></pmpcognacy>
</record>

<record>
	<id>114201</id>
	<word_id>15</word_id>
	<word>bone</word>
	<item>ʔi'ngit</item>
	<annotation></annotation>
	<loan></loan>
	<cognacy></cognacy>
	<pmpcognacy></pmpcognacy>
</record>

<record>
	<id>114202</id>
	<word_id>16</word_id>
	<word>intestines</word>
	<item>ʔɨ'gɨs</item>
	<annotation></annotation>
	<loan></loan>
	<cognacy>65</cognacy>
	<pmpcognacy></pmpcognacy>
</record>

<record>
	<id>114203</id>
	<word_id>17</word_id>
	<word>liver</word>
	<item>'ʔatɨy</item>
	<annotation></annotation>
	<loan></loan>
	<cognacy>1</cognacy>
	<pmpcognacy></pmpcognacy>
</record>

<record>
	<id>114204</id>
	<word_id>18</word_id>
	<word>breast</word>
	<item>'soso</item>
	<annotation></annotation>
	<loan></loan>
	<cognacy>1</cognacy>
	<pmpcognacy></pmpcognacy>
</record>

<record>
	<id>114205</id>
	<word_id>18</word_id>
	<word>breast</word>
	<item>pa'gaʔiw</item>
	<annotation>chest</annotation>
	<loan></loan>
	<cognacy>x</cognacy>
	<pmpcognacy></pmpcognacy>
</record>

<record>
	<id>114206</id>
	<word_id>19</word_id>
	<word>shoulder</word>
	<item>'pokɨ</item>
	<annotation></annotation>
	<loan></loan>
	<cognacy>32</cognacy>
	<pmpcognacy></pmpcognacy>
</record>

<record>
	<id>114207</id>
	<word_id>20</word_id>
	<word>to know, be knowledgeable</word>
	<item>gik'kin</item>
	<annotation>know (a person)</annotation>
	<loan></loan>
	<cognacy>105</cognacy>
	<pmpcognacy></pmpcognacy>
</record>

<record>
	<id>114208</id>
	<word_id>22</word_id>
	<word>to fear</word>
	<item>ʔomɨg'yat</item>
	<annotation></annotation>
	<loan></loan>
	<cognacy>30</cognacy>
	<pmpcognacy></pmpcognacy>
</record>

<record>
	<id>114209</id>
	<word_id>23</word_id>
	<word>blood</word>
	<item>ba'sa</item>
	<annotation></annotation>
	<loan></loan>
	<cognacy></cognacy>
	<pmpcognacy></pmpcognacy>
</record>

<record>
	<id>114210</id>
	<word_id>24</word_id>
	<word>head</word>
	<item>ʔu'wo</item>
	<annotation></annotation>
	<loan></loan>
	<cognacy>1</cognacy>
	<pmpcognacy></pmpcognacy>
</record>

<record>
	<id>114211</id>
	<word_id>25</word_id>
	<word>neck</word>
	<item>ba'gang</item>
	<annotation></annotation>
	<loan></loan>
	<cognacy>73</cognacy>
	<pmpcognacy></pmpcognacy>
</record>

<record>
	<id>114212</id>
	<word_id>26</word_id>
	<word>hair</word>
	<item>bo'ʔok</item>
	<annotation></annotation>
	<loan></loan>
	<cognacy>1,65</cognacy>
	<pmpcognacy></pmpcognacy>
</record>

<record>
	<id>114213</id>
	<word_id>27</word_id>
	<word>nose</word>
	<item>ʔɨ'ʔɨng</item>
	<annotation></annotation>
	<loan></loan>
	<cognacy>85</cognacy>
	<pmpcognacy></pmpcognacy>
</record>

<record>
	<id>114214</id>
	<word_id>29</word_id>
	<word>to sniff, smell</word>
	<item>'songsong</item>
	<annotation></annotation>
	<loan></loan>
	<cognacy>9</cognacy>
	<pmpcognacy></pmpcognacy>
</record>

<record>
	<id>114215</id>
	<word_id>30</word_id>
	<word>mouth</word>
	<item>to'pɨk</item>
	<annotation></annotation>
	<loan></loan>
	<cognacy>34</cognacy>
	<pmpcognacy></pmpcognacy>
</record>

<record>
	<id>114216</id>
	<word_id>31</word_id>
	<word>tooth</word>
	<item>bab'ʔa</item>
	<annotation>teeth</annotation>
	<loan></loan>
	<cognacy>72</cognacy>
	<pmpcognacy></pmpcognacy>
</record>

<record>
	<id>114217</id>
	<word_id>32</word_id>
	<word>tongue</word>
	<item>di'la</item>
	<annotation></annotation>
	<loan></loan>
	<cognacy>4</cognacy>
	<pmpcognacy></pmpcognacy>
</record>

<record>
	<id>114218</id>
	<word_id>33</word_id>
	<word>to laugh</word>
	<item>mɨnʔɨ'yɨk</item>
	<annotation></annotation>
	<loan></loan>
	<cognacy>26,37</cognacy>
	<pmpcognacy></pmpcognacy>
</record>

<record>
	<id>114219</id>
	<word_id>34</word_id>
	<word>to cry</word>
	<item>min'ʔaga</item>
	<annotation></annotation>
	<loan></loan>
	<cognacy>21</cognacy>
	<pmpcognacy></pmpcognacy>
</record>

<record>
	<id>114220</id>
	<word_id>35</word_id>
	<word>to vomit</word>
	<item>'ʔota</item>
	<annotation></annotation>
	<loan></loan>
	<cognacy>1</cognacy>
	<pmpcognacy></pmpcognacy>
</record>

<record>
	<id>114221</id>
	<word_id>36</word_id>
	<word>to spit</word>
	<item>top'pa</item>
	<annotation></annotation>
	<loan></loan>
	<cognacy>44</cognacy>
	<pmpcognacy></pmpcognacy>
</record>

<record>
	<id>114222</id>
	<word_id>37</word_id>
	<word>to eat</word>
	<item>ma'ngan</item>
	<annotation></annotation>
	<loan></loan>
	<cognacy>1,14</cognacy>
	<pmpcognacy></pmpcognacy>
</record>

<record>
	<id>114223</id>
	<word_id>38</word_id>
	<word>to chew</word>
	<item>mɨ'ma</item>
	<annotation>*betel chew</annotation>
	<loan></loan>
	<cognacy>1</cognacy>
	<pmpcognacy></pmpcognacy>
</record>

<record>
	<id>114224</id>
	<word_id>39</word_id>
	<word>to cook</word>
	<item>lom'wag</item>
	<annotation>30. *to boil</annotation>
	<loan></loan>
	<cognacy>33</cognacy>
	<pmpcognacy></pmpcognacy>
</record>

<record>
	<id>114225</id>
	<word_id>39</word_id>
	<word>to cook</word>
	<item>mɨn'ʔoto</item>
	<annotation></annotation>
	<loan></loan>
	<cognacy>20</cognacy>
	<pmpcognacy></pmpcognacy>
</record>

<record>
	<id>114226</id>
	<word_id>40</word_id>
	<word>to drink</word>
	<item>ʔomi'nom</item>
	<annotation></annotation>
	<loan></loan>
	<cognacy>1</cognacy>
	<pmpcognacy></pmpcognacy>
</record>

<record>
	<id>114227</id>
	<word_id>41</word_id>
	<word>to bite</word>
	<item>ba'ngɨt</item>
	<annotation></annotation>
	<loan></loan>
	<cognacy>33</cognacy>
	<pmpcognacy></pmpcognacy>
</record>

<record>
	<id>114228</id>
	<word_id>42</word_id>
	<word>to suck</word>
	<item>'sopsopɬ</item>
	<annotation></annotation>
	<loan></loan>
	<cognacy>1,73</cognacy>
	<pmpcognacy></pmpcognacy>
</record>

<record>
	<id>114229</id>
	<word_id>43</word_id>
	<word>ear</word>
	<item>'ʔinga</item>
	<annotation></annotation>
	<loan></loan>
	<cognacy>1,38</cognacy>
	<pmpcognacy></pmpcognacy>
</record>

<record>
	<id>114230</id>
	<word_id>44</word_id>
	<word>to hear</word>
	<item>dɨng'ngɨ</item>
	<annotation></annotation>
	<loan></loan>
	<cognacy>1</cognacy>
	<pmpcognacy></pmpcognacy>
</record>

<record>
	<id>114231</id>
	<word_id>45</word_id>
	<word>eye</word>
	<item>ma'ta</item>
	<annotation></annotation>
	<loan></loan>
	<cognacy>1</cognacy>
	<pmpcognacy></pmpcognacy>
</record>

<record>
	<id>114232</id>
	<word_id>46</word_id>
	<word>to see</word>
	<item>'ʔila</item>
	<annotation></annotation>
	<loan></loan>
	<cognacy>26</cognacy>
	<pmpcognacy></pmpcognacy>
</record>

<record>
	<id>114233</id>
	<word_id>48</word_id>
	<word>to sleep</word>
	<item>masɨ'yɨp</item>
	<annotation></annotation>
	<loan></loan>
	<cognacy>31</cognacy>
	<pmpcognacy></pmpcognacy>
</record>

<record>
	<id>114234</id>
	<word_id>50</word_id>
	<word>to dream</word>
	<item>ʔiʔi'taw</item>
	<annotation></annotation>
	<loan></loan>
	<cognacy>31</cognacy>
	<pmpcognacy></pmpcognacy>
</record>

<record>
	<id>114235</id>
	<word_id>51</word_id>
	<word>to sit</word>
	<item>ʔitok'do</item>
	<annotation></annotation>
	<loan></loan>
	<cognacy>50,51</cognacy>
	<pmpcognacy></pmpcognacy>
</record>

<record>
	<id>114236</id>
	<word_id>52</word_id>
	<word>to stand</word>
	<item>ʔitak'dɨg</item>
	<annotation></annotation>
	<loan></loan>
	<cognacy>85,86</cognacy>
	<pmpcognacy></pmpcognacy>
</record>

<record>
	<id>114237</id>
	<word_id>53</word_id>
	<word>person/human being</word>
	<item>ʔipo'gaw</item>
	<annotation></annotation>
	<loan></loan>
	<cognacy>30</cognacy>
	<pmpcognacy></pmpcognacy>
</record>

<record>
	<id>114238</id>
	<word_id>54</word_id>
	<word>man/male</word>
	<item>la'laki</item>
	<annotation></annotation>
	<loan></loan>
	<cognacy>2,99</cognacy>
	<pmpcognacy></pmpcognacy>
</record>

<record>
	<id>114239</id>
	<word_id>55</word_id>
	<word>woman/female</word>
	<item>ba'baʔi</item>
	<annotation></annotation>
	<loan></loan>
	<cognacy>1,105</cognacy>
	<pmpcognacy></pmpcognacy>
</record>

<record>
	<id>114240</id>
	<word_id>56</word_id>
	<word>child</word>
	<item>ʔo'nga</item>
	<annotation></annotation>
	<loan></loan>
	<cognacy>22</cognacy>
	<pmpcognacy></pmpcognacy>
</record>

<record>
	<id>114241</id>
	<word_id>57</word_id>
	<word>husband</word>
	<item>ʔa'sawa ay la'laki</item>
	<annotation></annotation>
	<loan></loan>
	<cognacy>2</cognacy>
	<pmpcognacy></pmpcognacy>
</record>

<record>
	<id>114242</id>
	<word_id>58</word_id>
	<word>wife</word>
	<item>ʔa'sawa ay ba'baʔi</item>
	<annotation></annotation>
	<loan></loan>
	<cognacy>1</cognacy>
	<pmpcognacy></pmpcognacy>
</record>

<record>
	<id>114243</id>
	<word_id>59</word_id>
	<word>mother</word>
	<item>'ʔina</item>
	<annotation></annotation>
	<loan></loan>
	<cognacy>1</cognacy>
	<pmpcognacy></pmpcognacy>
</record>

<record>
	<id>114244</id>
	<word_id>60</word_id>
	<word>father</word>
	<item>'ʔama</item>
	<annotation></annotation>
	<loan></loan>
	<cognacy>1</cognacy>
	<pmpcognacy></pmpcognacy>
</record>

<record>
	<id>114245</id>
	<word_id>61</word_id>
	<word>house</word>
	<item>ba'ʔɨy</item>
	<annotation></annotation>
	<loan></loan>
	<cognacy>14</cognacy>
	<pmpcognacy></pmpcognacy>
</record>

<record>
	<id>114246</id>
	<word_id>62</word_id>
	<word>thatch/roof</word>
	<item>ʔa'tɨp</item>
	<annotation></annotation>
	<loan></loan>
	<cognacy>1</cognacy>
	<pmpcognacy></pmpcognacy>
</record>

<record>
	<id>114247</id>
	<word_id>63</word_id>
	<word>name</word>
	<item>nga'dan</item>
	<annotation></annotation>
	<loan></loan>
	<cognacy>1,47</cognacy>
	<pmpcognacy></pmpcognacy>
</record>

<record>
	<id>114248</id>
	<word_id>64</word_id>
	<word>to say</word>
	<item>ka'nan</item>
	<annotation></annotation>
	<loan></loan>
	<cognacy>35,36</cognacy>
	<pmpcognacy></pmpcognacy>
</record>

<record>
	<id>114249</id>
	<word_id>65</word_id>
	<word>rope</word>
	<item>ta'li</item>
	<annotation></annotation>
	<loan></loan>
	<cognacy>1</cognacy>
	<pmpcognacy></pmpcognacy>
</record>

<record>
	<id>114250</id>
	<word_id>66</word_id>
	<word>to tie up, fasten</word>
	<item>ʔiba'ʔod</item>
	<annotation></annotation>
	<loan></loan>
	<cognacy>40</cognacy>
	<pmpcognacy></pmpcognacy>
</record>

<record>
	<id>114251</id>
	<word_id>67</word_id>
	<word>to sew</word>
	<item>'daʔit</item>
	<annotation></annotation>
	<loan></loan>
	<cognacy>2</cognacy>
	<pmpcognacy></pmpcognacy>
</record>

<record>
	<id>114252</id>
	<word_id>68</word_id>
	<word>needle</word>
	<item>'dagom</item>
	<annotation></annotation>
	<loan>L</loan>
	<cognacy>1</cognacy>
	<pmpcognacy></pmpcognacy>
</record>

<record>
	<id>114253</id>
	<word_id>69</word_id>
	<word>to hunt</word>
	<item>mɨnʔa'nop</item>
	<annotation></annotation>
	<loan></loan>
	<cognacy>1</cognacy>
	<pmpcognacy></pmpcognacy>
</record>

<record>
	<id>114254</id>
	<word_id>71</word_id>
	<word>to stab, pierce</word>
	<item>doy'ʔokɨn</item>
	<annotation></annotation>
	<loan></loan>
	<cognacy></cognacy>
	<pmpcognacy></pmpcognacy>
</record>

<record>
	<id>114255</id>
	<word_id>73</word_id>
	<word>to steal</word>
	<item>mɨn'ʔakɨw</item>
	<annotation></annotation>
	<loan></loan>
	<cognacy>1,54</cognacy>
	<pmpcognacy></pmpcognacy>
</record>

<record>
	<id>114256</id>
	<word_id>74</word_id>
	<word>to kill</word>
	<item>pa'tɨy</item>
	<annotation></annotation>
	<loan></loan>
	<cognacy>2</cognacy>
	<pmpcognacy></pmpcognacy>
</record>

<record>
	<id>114257</id>
	<word_id>75</word_id>
	<word>to die, be dead</word>
	<item>na'tɨy</item>
	<annotation>dead</annotation>
	<loan></loan>
	<cognacy>1</cognacy>
	<pmpcognacy></pmpcognacy>
</record>

<record>
	<id>114258</id>
	<word_id>77</word_id>
	<word>to scratch</word>
	<item>min-ga'tɨ</item>
	<annotation>itch</annotation>
	<loan></loan>
	<cognacy>37,41</cognacy>
	<pmpcognacy></pmpcognacy>
</record>

<record>
	<id>114259</id>
	<word_id>77</word_id>
	<word>to scratch</word>
	<item>kot'kot</item>
	<annotation></annotation>
	<loan></loan>
	<cognacy>21</cognacy>
	<pmpcognacy></pmpcognacy>
</record>

<record>
	<id>114260</id>
	<word_id>78</word_id>
	<word>to cut, hack</word>
	<item>gɨdgɨ'dɨn</item>
	<annotation></annotation>
	<loan></loan>
	<cognacy>45</cognacy>
	<pmpcognacy></pmpcognacy>
</record>

<record>
	<id>114261</id>
	<word_id>79</word_id>
	<word>stick/wood</word>
	<item>'kaʔiw</item>
	<annotation></annotation>
	<loan></loan>
	<cognacy>1</cognacy>
	<pmpcognacy></pmpcognacy>
</record>

<record>
	<id>114262</id>
	<word_id>81</word_id>
	<word>sharp</word>
	<item>mɨnta'dɨm</item>
	<annotation></annotation>
	<loan></loan>
	<cognacy>1</cognacy>
	<pmpcognacy></pmpcognacy>
</record>

<record>
	<id>114263</id>
	<word_id>82</word_id>
	<word>dull, blunt</word>
	<item>ngo'dɨl</item>
	<annotation></annotation>
	<loan></loan>
	<cognacy>43</cognacy>
	<pmpcognacy></pmpcognacy>
</record>

<record>
	<id>114264</id>
	<word_id>83</word_id>
	<word>to work</word>
	<item>lo'mokso</item>
	<annotation></annotation>
	<loan></loan>
	<cognacy></cognacy>
	<pmpcognacy></pmpcognacy>
</record>

<record>
	<id>114265</id>
	<word_id>84</word_id>
	<word>to plant</word>
	<item>mɨnʔis'ʔɨk</item>
	<annotation></annotation>
	<loan></loan>
	<cognacy>28</cognacy>
	<pmpcognacy></pmpcognacy>
</record>

<record>
	<id>114266</id>
	<word_id>85</word_id>
	<word>to choose</word>
	<item>pili'yɨn</item>
	<annotation></annotation>
	<loan></loan>
	<cognacy>1</cognacy>
	<pmpcognacy></pmpcognacy>
</record>

<record>
	<id>114267</id>
	<word_id>88</word_id>
	<word>to squeeze</word>
	<item>pɨspɨ'sɨn</item>
	<annotation></annotation>
	<loan></loan>
	<cognacy>18</cognacy>
	<pmpcognacy></pmpcognacy>
</record>

<record>
	<id>114268</id>
	<word_id>89</word_id>
	<word>to hold</word>
	<item>gɨn'ʔan</item>
	<annotation></annotation>
	<loan></loan>
	<cognacy>43</cognacy>
	<pmpcognacy></pmpcognacy>
</record>

<record>
	<id>114269</id>
	<word_id>90</word_id>
	<word>to dig</word>
	<item>mɨn'kaʔob</item>
	<annotation></annotation>
	<loan></loan>
	<cognacy>77</cognacy>
	<pmpcognacy></pmpcognacy>
</record>

<record>
	<id>114270</id>
	<word_id>91</word_id>
	<word>to buy</word>
	<item>la'kowan</item>
	<annotation></annotation>
	<loan></loan>
	<cognacy>27</cognacy>
	<pmpcognacy></pmpcognacy>
</record>

<record>
	<id>114271</id>
	<word_id>93</word_id>
	<word>to pound, beat</word>
	<item>mɨn'bayo</item>
	<annotation></annotation>
	<loan></loan>
	<cognacy>1</cognacy>
	<pmpcognacy></pmpcognacy>
</record>

<record>
	<id>114272</id>
	<word_id>94</word_id>
	<word>to throw</word>
	<item>ʔiga'yang</item>
	<annotation></annotation>
	<loan></loan>
	<cognacy>101</cognacy>
	<pmpcognacy></pmpcognacy>
</record>

<record>
	<id>114273</id>
	<word_id>95</word_id>
	<word>to fall</word>
	<item>ma'ʔɨkdag</item>
	<annotation></annotation>
	<loan></loan>
	<cognacy>55</cognacy>
	<pmpcognacy></pmpcognacy>
</record>

<record>
	<id>114274</id>
	<word_id>96</word_id>
	<word>dog</word>
	<item>'ʔaso</item>
	<annotation></annotation>
	<loan></loan>
	<cognacy>1</cognacy>
	<pmpcognacy></pmpcognacy>
</record>

<record>
	<id>114275</id>
	<word_id>97</word_id>
	<word>bird</word>
	<item>'koyat</item>
	<annotation></annotation>
	<loan></loan>
	<cognacy></cognacy>
	<pmpcognacy></pmpcognacy>
</record>

<record>
	<id>114276</id>
	<word_id>98</word_id>
	<word>egg</word>
	<item>ʔit'log</item>
	<annotation></annotation>
	<loan></loan>
	<cognacy>1,24</cognacy>
	<pmpcognacy></pmpcognacy>
</record>

<record>
	<id>114277</id>
	<word_id>99</word_id>
	<word>feather</word>
	<item>'gatod</item>
	<annotation></annotation>
	<loan></loan>
	<cognacy>33</cognacy>
	<pmpcognacy></pmpcognacy>
</record>

<record>
	<id>114278</id>
	<word_id>100</word_id>
	<word>wing</word>
	<item>pay'yak</item>
	<annotation></annotation>
	<loan></loan>
	<cognacy>33,40</cognacy>
	<pmpcognacy></pmpcognacy>
</record>

<record>
	<id>114279</id>
	<word_id>101</word_id>
	<word>to fly</word>
	<item>to'mayaw</item>
	<annotation></annotation>
	<loan></loan>
	<cognacy>83,38</cognacy>
	<pmpcognacy></pmpcognacy>
</record>

<record>
	<id>114280</id>
	<word_id>102</word_id>
	<word>rat</word>
	<item>'ʔotot</item>
	<annotation></annotation>
	<loan></loan>
	<cognacy>25</cognacy>
	<pmpcognacy></pmpcognacy>
</record>

<record>
	<id>114281</id>
	<word_id>104</word_id>
	<word>fat/grease</word>
	<item>ta'ba</item>
	<annotation>104. fat (n.)</annotation>
	<loan></loan>
	<cognacy>23</cognacy>
	<pmpcognacy></pmpcognacy>
</record>

<record>
	<id>114282</id>
	<word_id>105</word_id>
	<word>tail</word>
	<item>'ʔiko</item>
	<annotation></annotation>
	<loan></loan>
	<cognacy>1</cognacy>
	<pmpcognacy></pmpcognacy>
</record>

<record>
	<id>114283</id>
	<word_id>106</word_id>
	<word>snake</word>
	<item>'ʔowɨg</item>
	<annotation></annotation>
	<loan></loan>
	<cognacy>2,33</cognacy>
	<pmpcognacy></pmpcognacy>
</record>

<record>
	<id>114284</id>
	<word_id>107</word_id>
	<word>worm (earthworm)</word>
	<item>kɨ'ʔang</item>
	<annotation></annotation>
	<loan></loan>
	<cognacy>18</cognacy>
	<pmpcognacy></pmpcognacy>
</record>

<record>
	<id>114285</id>
	<word_id>108</word_id>
	<word>louse</word>
	<item>ko'to</item>
	<annotation>lice (head)</annotation>
	<loan></loan>
	<cognacy>1</cognacy>
	<pmpcognacy></pmpcognacy>
</record>

<record>
	<id>114286</id>
	<word_id>109</word_id>
	<word>mosquito</word>
	<item>la'mok</item>
	<annotation></annotation>
	<loan></loan>
	<cognacy>1,33</cognacy>
	<pmpcognacy></pmpcognacy>
</record>

<record>
	<id>114287</id>
	<word_id>110</word_id>
	<word>spider</word>
	<item>ʔating'kawa</item>
	<annotation></annotation>
	<loan></loan>
	<cognacy>1,71</cognacy>
	<pmpcognacy></pmpcognacy>
</record>

<record>
	<id>114288</id>
	<word_id>111</word_id>
	<word>fish</word>
	<item>ʔi'kan</item>
	<annotation></annotation>
	<loan></loan>
	<cognacy>1</cognacy>
	<pmpcognacy></pmpcognacy>
</record>

<record>
	<id>114289</id>
	<word_id>112</word_id>
	<word>rotten</word>
	<item>ma'donot</item>
	<annotation></annotation>
	<loan>L</loan>
	<cognacy></cognacy>
	<pmpcognacy></pmpcognacy>
</record>

<record>
	<id>114290</id>
	<word_id>114</word_id>
	<word>leaf</word>
	<item>'tobo</item>
	<annotation></annotation>
	<loan></loan>
	<cognacy>23</cognacy>
	<pmpcognacy></pmpcognacy>
</record>

<record>
	<id>114291</id>
	<word_id>115</word_id>
	<word>root</word>
	<item>la'mot</item>
	<annotation></annotation>
	<loan></loan>
	<cognacy>3</cognacy>
	<pmpcognacy></pmpcognacy>
</record>

<record>
	<id>114292</id>
	<word_id>116</word_id>
	<word>flower</word>
	<item>'sabong</item>
	<annotation></annotation>
	<loan></loan>
	<cognacy>1,24</cognacy>
	<pmpcognacy></pmpcognacy>
</record>

<record>
	<id>114293</id>
	<word_id>117</word_id>
	<word>fruit</word>
	<item>bɨ'gas</item>
	<annotation></annotation>
	<loan></loan>
	<cognacy>15</cognacy>
	<pmpcognacy></pmpcognacy>
</record>

<record>
	<id>114294</id>
	<word_id>119</word_id>
	<word>earth/soil</word>
	<item>'lota</item>
	<annotation></annotation>
	<loan></loan>
	<cognacy>25</cognacy>
	<pmpcognacy></pmpcognacy>
</record>

<record>
	<id>114295</id>
	<word_id>120</word_id>
	<word>stone</word>
	<item>ba'to</item>
	<annotation></annotation>
	<loan></loan>
	<cognacy>1</cognacy>
	<pmpcognacy></pmpcognacy>
</record>

<record>
	<id>114296</id>
	<word_id>121</word_id>
	<word>sand</word>
	<item>la'gan</item>
	<annotation></annotation>
	<loan></loan>
	<cognacy>38</cognacy>
	<pmpcognacy></pmpcognacy>
</record>

<record>
	<id>114297</id>
	<word_id>122</word_id>
	<word>water</word>
	<item>da'nom</item>
	<annotation></annotation>
	<loan></loan>
	<cognacy>1</cognacy>
	<pmpcognacy></pmpcognacy>
</record>

<record>
	<id>114298</id>
	<word_id>124</word_id>
	<word>sea</word>
	<item>bay'bay</item>
	<annotation>from Ilokano</annotation>
	<loan>L</loan>
	<cognacy>28</cognacy>
	<pmpcognacy></pmpcognacy>
</record>

<record>
	<id>114299</id>
	<word_id>125</word_id>
	<word>salt</word>
	<item>ʔa'sin</item>
	<annotation></annotation>
	<loan></loan>
	<cognacy>3</cognacy>
	<pmpcognacy></pmpcognacy>
</record>

<record>
	<id>114300</id>
	<word_id>126</word_id>
	<word>lake</word>
	<item>po'song</item>
	<annotation></annotation>
	<loan></loan>
	<cognacy>18</cognacy>
	<pmpcognacy></pmpcognacy>
</record>

<record>
	<id>114301</id>
	<word_id>127</word_id>
	<word>woods/forest</word>
	<item>'pagpag</item>
	<annotation></annotation>
	<loan></loan>
	<cognacy>103</cognacy>
	<pmpcognacy></pmpcognacy>
</record>

<record>
	<id>114302</id>
	<word_id>128</word_id>
	<word>sky</word>
	<item>da'ya</item>
	<annotation></annotation>
	<loan></loan>
	<cognacy>22</cognacy>
	<pmpcognacy></pmpcognacy>
</record>

<record>
	<id>114303</id>
	<word_id>129</word_id>
	<word>moon</word>
	<item>'bowan</item>
	<annotation></annotation>
	<loan></loan>
	<cognacy>1</cognacy>
	<pmpcognacy></pmpcognacy>
</record>

<record>
	<id>114304</id>
	<word_id>130</word_id>
	<word>star</word>
	<item>ta'law</item>
	<annotation></annotation>
	<loan></loan>
	<cognacy>25</cognacy>
	<pmpcognacy></pmpcognacy>
</record>

<record>
	<id>114305</id>
	<word_id>131</word_id>
	<word>cloud</word>
	<item>li'boʔo</item>
	<annotation></annotation>
	<loan></loan>
	<cognacy>50</cognacy>
	<pmpcognacy></pmpcognacy>
</record>

<record>
	<id>114306</id>
	<word_id>133</word_id>
	<word>rain</word>
	<item>ʔo'dan</item>
	<annotation></annotation>
	<loan></loan>
	<cognacy>1</cognacy>
	<pmpcognacy></pmpcognacy>
</record>

<record>
	<id>114307</id>
	<word_id>134</word_id>
	<word>thunder</word>
	<item>ki'do</item>
	<annotation></annotation>
	<loan></loan>
	<cognacy>2,92</cognacy>
	<pmpcognacy></pmpcognacy>
</record>

<record>
	<id>114308</id>
	<word_id>135</word_id>
	<word>lightning</word>
	<item>ba'gilat</item>
	<annotation></annotation>
	<loan></loan>
	<cognacy>1,83</cognacy>
	<pmpcognacy></pmpcognacy>
</record>

<record>
	<id>114309</id>
	<word_id>136</word_id>
	<word>wind</word>
	<item>da'gɨm</item>
	<annotation></annotation>
	<loan></loan>
	<cognacy>40</cognacy>
	<pmpcognacy></pmpcognacy>
</record>

<record>
	<id>114310</id>
	<word_id>137</word_id>
	<word>to blow</word>
	<item>sip'ʔoy</item>
	<annotation></annotation>
	<loan></loan>
	<cognacy>33</cognacy>
	<pmpcognacy></pmpcognacy>
</record>

<record>
	<id>114311</id>
	<word_id>138</word_id>
	<word>warm</word>
	<item>min'poʔos</item>
	<annotation>hot (as in water)</annotation>
	<loan></loan>
	<cognacy></cognacy>
	<pmpcognacy></pmpcognacy>
</record>

<record>
	<id>114312</id>
	<word_id>139</word_id>
	<word>cold</word>
	<item>mɨn'tɨdɨk</item>
	<annotation></annotation>
	<loan></loan>
	<cognacy>117</cognacy>
	<pmpcognacy></pmpcognacy>
</record>

<record>
	<id>114313</id>
	<word_id>140</word_id>
	<word>dry</word>
	<item>na'ʔango</item>
	<annotation>dry (not wet)</annotation>
	<loan></loan>
	<cognacy>1</cognacy>
	<pmpcognacy></pmpcognacy>
</record>

<record>
	<id>114314</id>
	<word_id>140</word_id>
	<word>dry</word>
	<item>ʔisap'ʔɨy</item>
	<annotation>to dry</annotation>
	<loan></loan>
	<cognacy>40</cognacy>
	<pmpcognacy></pmpcognacy>
</record>

<record>
	<id>114315</id>
	<word_id>141</word_id>
	<word>wet</word>
	<item>natɨm'bɨ</item>
	<annotation></annotation>
	<loan></loan>
	<cognacy></cognacy>
	<pmpcognacy></pmpcognacy>
</record>

<record>
	<id>114316</id>
	<word_id>142</word_id>
	<word>heavy</word>
	<item>mɨndag'sɨn</item>
	<annotation></annotation>
	<loan></loan>
	<cognacy>23</cognacy>
	<pmpcognacy></pmpcognacy>
</record>

<record>
	<id>114317</id>
	<word_id>143</word_id>
	<word>fire</word>
	<item>ʔa'poy</item>
	<annotation></annotation>
	<loan></loan>
	<cognacy>1</cognacy>
	<pmpcognacy></pmpcognacy>
</record>

<record>
	<id>114318</id>
	<word_id>144</word_id>
	<word>to burn</word>
	<item>sɨg'bɨn</item>
	<annotation></annotation>
	<loan></loan>
	<cognacy>97</cognacy>
	<pmpcognacy></pmpcognacy>
</record>

<record>
	<id>114319</id>
	<word_id>145</word_id>
	<word>smoke</word>
	<item>ʔa'sok</item>
	<annotation></annotation>
	<loan></loan>
	<cognacy>2,53</cognacy>
	<pmpcognacy></pmpcognacy>
</record>

<record>
	<id>114320</id>
	<word_id>146</word_id>
	<word>ash</word>
	<item>'dapo</item>
	<annotation></annotation>
	<loan></loan>
	<cognacy>17</cognacy>
	<pmpcognacy></pmpcognacy>
</record>

<record>
	<id>114321</id>
	<word_id>147</word_id>
	<word>black</word>
	<item>ngiti'yan</item>
	<annotation></annotation>
	<loan></loan>
	<cognacy></cognacy>
	<pmpcognacy></pmpcognacy>
</record>

<record>
	<id>114322</id>
	<word_id>148</word_id>
	<word>white</word>
	<item>po'law</item>
	<annotation></annotation>
	<loan></loan>
	<cognacy>3</cognacy>
	<pmpcognacy></pmpcognacy>
</record>

<record>
	<id>114323</id>
	<word_id>149</word_id>
	<word>red</word>
	<item>mɨn-ga'dangdang</item>
	<annotation></annotation>
	<loan></loan>
	<cognacy></cognacy>
	<pmpcognacy></pmpcognacy>
</record>

<record>
	<id>114324</id>
	<word_id>150</word_id>
	<word>yellow</word>
	<item>kinaʔo'nɨgan</item>
	<annotation></annotation>
	<loan></loan>
	<cognacy>1</cognacy>
	<pmpcognacy></pmpcognacy>
</record>

<record>
	<id>114325</id>
	<word_id>151</word_id>
	<word>green</word>
	<item>'bildi</item>
	<annotation></annotation>
	<loan></loan>
	<cognacy></cognacy>
	<pmpcognacy></pmpcognacy>
</record>

<record>
	<id>114326</id>
	<word_id>152</word_id>
	<word>small</word>
	<item>tɨʔɨ'tɨʔɨn</item>
	<annotation></annotation>
	<loan></loan>
	<cognacy></cognacy>
	<pmpcognacy></pmpcognacy>
</record>

<record>
	<id>114327</id>
	<word_id>153</word_id>
	<word>big</word>
	<item>dak'kɨl</item>
	<annotation></annotation>
	<loan></loan>
	<cognacy>22,102</cognacy>
	<pmpcognacy></pmpcognacy>
</record>

<record>
	<id>114328</id>
	<word_id>154</word_id>
	<word>short</word>
	<item>ʔap'tik</item>
	<annotation>short (person)</annotation>
	<loan></loan>
	<cognacy>49</cognacy>
	<pmpcognacy></pmpcognacy>
</record>

<record>
	<id>114329</id>
	<word_id>154</word_id>
	<word>short</word>
	<item>ʔap'tik</item>
	<annotation>short (object)</annotation>
	<loan></loan>
	<cognacy>49</cognacy>
	<pmpcognacy></pmpcognacy>
</record>

<record>
	<id>114330</id>
	<word_id>155</word_id>
	<word>long</word>
	<item>ʔan'do</item>
	<annotation></annotation>
	<loan></loan>
	<cognacy>1</cognacy>
	<pmpcognacy></pmpcognacy>
</record>

<record>
	<id>114331</id>
	<word_id>156</word_id>
	<word>thin</word>
	<item>mɨn'yapit</item>
	<annotation></annotation>
	<loan></loan>
	<cognacy>1,2</cognacy>
	<pmpcognacy></pmpcognacy>
</record>

<record>
	<id>114332</id>
	<word_id>157</word_id>
	<word>thick</word>
	<item>mɨnsɨ'dɨ</item>
	<annotation></annotation>
	<loan></loan>
	<cognacy>34</cognacy>
	<pmpcognacy></pmpcognacy>
</record>

<record>
	<id>114333</id>
	<word_id>158</word_id>
	<word>narrow</word>
	<item>nali'pit</item>
	<annotation></annotation>
	<loan></loan>
	<cognacy>1</cognacy>
	<pmpcognacy></pmpcognacy>
</record>

<record>
	<id>114334</id>
	<word_id>159</word_id>
	<word>wide</word>
	<item>ʔanna'wa</item>
	<annotation></annotation>
	<loan></loan>
	<cognacy>1,59</cognacy>
	<pmpcognacy></pmpcognacy>
</record>

<record>
	<id>114335</id>
	<word_id>160</word_id>
	<word>painful, sick</word>
	<item>sa'kit</item>
	<annotation></annotation>
	<loan></loan>
	<cognacy>1</cognacy>
	<pmpcognacy></pmpcognacy>
</record>

<record>
	<id>114336</id>
	<word_id>161</word_id>
	<word>shy, ashamed</word>
	<item>maba'ʔin</item>
	<annotation></annotation>
	<loan></loan>
	<cognacy>25</cognacy>
	<pmpcognacy></pmpcognacy>
</record>

<record>
	<id>114337</id>
	<word_id>162</word_id>
	<word>old</word>
	<item>na'bayag</item>
	<annotation>old (objects)</annotation>
	<loan></loan>
	<cognacy>x</cognacy>
	<pmpcognacy></pmpcognacy>
</record>

<record>
	<id>114338</id>
	<word_id>162</word_id>
	<word>old</word>
	<item>naba'kɨs</item>
	<annotation>old woman</annotation>
	<loan>L</loan>
	<cognacy>x</cognacy>
	<pmpcognacy></pmpcognacy>
</record>

<record>
	<id>114339</id>
	<word_id>163</word_id>
	<word>new</word>
	<item>ba'lo</item>
	<annotation></annotation>
	<loan></loan>
	<cognacy>1,54</cognacy>
	<pmpcognacy></pmpcognacy>
</record>

<record>
	<id>114340</id>
	<word_id>164</word_id>
	<word>good</word>
	<item>ʔa'may</item>
	<annotation></annotation>
	<loan>L</loan>
	<cognacy></cognacy>
	<pmpcognacy></pmpcognacy>
</record>

<record>
	<id>114341</id>
	<word_id>165</word_id>
	<word>bad, evil</word>
	<item>nga'wi</item>
	<annotation></annotation>
	<loan></loan>
	<cognacy>35,84</cognacy>
	<pmpcognacy></pmpcognacy>
</record>

<record>
	<id>114342</id>
	<word_id>167</word_id>
	<word>night</word>
	<item>la'bi</item>
	<annotation></annotation>
	<loan></loan>
	<cognacy>21</cognacy>
	<pmpcognacy></pmpcognacy>
</record>

<record>
	<id>114343</id>
	<word_id>168</word_id>
	<word>day</word>
	<item>'ʔagɨw</item>
	<annotation></annotation>
	<loan></loan>
	<cognacy>1,54</cognacy>
	<pmpcognacy></pmpcognacy>
</record>

<record>
	<id>114344</id>
	<word_id>169</word_id>
	<word>year</word>
	<item>taw'ʔɨn</item>
	<annotation></annotation>
	<loan></loan>
	<cognacy>1,72</cognacy>
	<pmpcognacy></pmpcognacy>
</record>

<record>
	<id>114345</id>
	<word_id>170</word_id>
	<word>when?</word>
	<item>tongo'na</item>
	<annotation></annotation>
	<loan></loan>
	<cognacy></cognacy>
	<pmpcognacy></pmpcognacy>
</record>

<record>
	<id>114346</id>
	<word_id>171</word_id>
	<word>to hide</word>
	<item>ʔi'gago</item>
	<annotation></annotation>
	<loan></loan>
	<cognacy></cognacy>
	<pmpcognacy></pmpcognacy>
</record>

<record>
	<id>114347</id>
	<word_id>172</word_id>
	<word>to climb</word>
	<item>ka'ʔab</item>
	<annotation></annotation>
	<loan></loan>
	<cognacy>17,53</cognacy>
	<pmpcognacy></pmpcognacy>
</record>

<record>
	<id>114348</id>
	<word_id>176</word_id>
	<word>below</word>
	<item>'silok</item>
	<annotation>under</annotation>
	<loan></loan>
	<cognacy>35,31</cognacy>
	<pmpcognacy></pmpcognacy>
</record>

<record>
	<id>114349</id>
	<word_id>179</word_id>
	<word>near</word>
	<item>ʔa'sagʔɨn</item>
	<annotation></annotation>
	<loan></loan>
	<cognacy>47,49</cognacy>
	<pmpcognacy></pmpcognacy>
</record>

<record>
	<id>114350</id>
	<word_id>180</word_id>
	<word>far</word>
	<item>ʔadda'wi</item>
	<annotation></annotation>
	<loan></loan>
	<cognacy>1,36</cognacy>
	<pmpcognacy></pmpcognacy>
</record>

<record>
	<id>114351</id>
	<word_id>181</word_id>
	<word>where?</word>
	<item>ʔin'to</item>
	<annotation></annotation>
	<loan></loan>
	<cognacy>1,28</cognacy>
	<pmpcognacy></pmpcognacy>
</record>

<record>
	<id>114352</id>
	<word_id>188</word_id>
	<word>what?</word>
	<item>si'no</item>
	<annotation></annotation>
	<loan></loan>
	<cognacy>2,21</cognacy>
	<pmpcognacy></pmpcognacy>
</record>

<record>
	<id>114353</id>
	<word_id>189</word_id>
	<word>who?</word>
	<item>si'no</item>
	<annotation></annotation>
	<loan></loan>
	<cognacy>14,47</cognacy>
	<pmpcognacy></pmpcognacy>
</record>

<record>
	<id>114354</id>
	<word_id>190</word_id>
	<word>other</word>
	<item>tɨ'kɨn</item>
	<annotation></annotation>
	<loan></loan>
	<cognacy>34</cognacy>
	<pmpcognacy></pmpcognacy>
</record>

<record>
	<id>114355</id>
	<word_id>191</word_id>
	<word>all</word>
	<item>ʔam'ʔin</item>
	<annotation></annotation>
	<loan></loan>
	<cognacy>1</cognacy>
	<pmpcognacy></pmpcognacy>
</record>

<record>
	<id>114356</id>
	<word_id>193</word_id>
	<word>if</word>
	<item>mo</item>
	<annotation></annotation>
	<loan></loan>
	<cognacy>3,24</cognacy>
	<pmpcognacy></pmpcognacy>
</record>

<record>
	<id>114357</id>
	<word_id>194</word_id>
	<word>how?</word>
	<item>ka'ʔat na</item>
	<annotation>how many</annotation>
	<loan></loan>
	<cognacy>x</cognacy>
	<pmpcognacy></pmpcognacy>
</record>

<record>
	<id>114358</id>
	<word_id>195</word_id>
	<word>no, not</word>
	<item>ba'kɨn</item>
	<annotation></annotation>
	<loan></loan>
	<cognacy>26</cognacy>
	<pmpcognacy></pmpcognacy>
</record>

<record>
	<id>114359</id>
	<word_id>196</word_id>
	<word>to count</word>
	<item>'bilang</item>
	<annotation></annotation>
	<loan></loan>
	<cognacy>1</cognacy>
	<pmpcognacy></pmpcognacy>
</record>

<record>
	<id>114360</id>
	<word_id>197</word_id>
	<word>One</word>
	<item>ʔɨ'sa</item>
	<annotation></annotation>
	<loan></loan>
	<cognacy>1</cognacy>
	<pmpcognacy></pmpcognacy>
</record>

<record>
	<id>114361</id>
	<word_id>198</word_id>
	<word>Two</word>
	<item>do'wa</item>
	<annotation></annotation>
	<loan></loan>
	<cognacy>1</cognacy>
	<pmpcognacy></pmpcognacy>
</record>

<record>
	<id>114362</id>
	<word_id>199</word_id>
	<word>Three</word>
	<item>to'lo</item>
	<annotation></annotation>
	<loan></loan>
	<cognacy>1</cognacy>
	<pmpcognacy></pmpcognacy>
</record>

<record>
	<id>114363</id>
	<word_id>200</word_id>
	<word>Four</word>
	<item>ʔɨ'pat</item>
	<annotation></annotation>
	<loan></loan>
	<cognacy>1</cognacy>
	<pmpcognacy></pmpcognacy>
</record>

<record>
	<id>114364</id>
	<word_id>201</word_id>
	<word>Five</word>
	<item>li'ma</item>
	<annotation></annotation>
	<loan></loan>
	<cognacy>1</cognacy>
	<pmpcognacy></pmpcognacy>
</record>

<record>
	<id>114365</id>
	<word_id>202</word_id>
	<word>Six</word>
	<item>ʔɨ'nɨm</item>
	<annotation></annotation>
	<loan></loan>
	<cognacy>1</cognacy>
	<pmpcognacy></pmpcognacy>
</record>

<record>
	<id>114366</id>
	<word_id>203</word_id>
	<word>Seven</word>
	<item>pi'to</item>
	<annotation></annotation>
	<loan></loan>
	<cognacy>1</cognacy>
	<pmpcognacy></pmpcognacy>
</record>

<record>
	<id>114367</id>
	<word_id>204</word_id>
	<word>Eight</word>
	<item>wa'ʔo</item>
	<annotation></annotation>
	<loan></loan>
	<cognacy>3</cognacy>
	<pmpcognacy></pmpcognacy>
</record>

<record>
	<id>114368</id>
	<word_id>205</word_id>
	<word>Nine</word>
	<item>si'yam</item>
	<annotation></annotation>
	<loan></loan>
	<cognacy>9</cognacy>
	<pmpcognacy></pmpcognacy>
</record>

<record>
	<id>114369</id>
	<word_id>206</word_id>
	<word>Ten</word>
	<item>sim'po</item>
	<annotation></annotation>
	<loan></loan>
	<cognacy>5</cognacy>
	<pmpcognacy></pmpcognacy>
</record>

<record>
	<id>114370</id>
	<word_id>207</word_id>
	<word>Twenty</word>
	<item>dowam'poʔo</item>
	<annotation></annotation>
	<loan></loan>
	<cognacy>3,6</cognacy>
	<pmpcognacy></pmpcognacy>
</record>

<record>
	<id>114371</id>
	<word_id>209</word_id>
	<word>One Hundred</word>
	<item>ga'sot</item>
	<annotation></annotation>
	<loan></loan>
	<cognacy>4,50</cognacy>
	<pmpcognacy></pmpcognacy>
</record>

<record>
	<id>114372</id>
	<word_id>210</word_id>
	<word>One Thousand</word>
	<item>'libo</item>
	<annotation></annotation>
	<loan></loan>
	<cognacy>5</cognacy>
	<pmpcognacy></pmpcognacy>
</record>

